docs/changelog.md
docs/contributing.md
docs/documentation.md
docs/index.md
docs/tests_results.md
mvola_api/__init__.py
mvola_api/auth.py
mvola_api/client.py
mvola_api/constants.py
mvola_api/exceptions.py
mvola_api/transaction.py
mvola_api/utils.py
mvola_api_lib-1.4.1.dist-info/LICENSE
mvola_api_lib-1.4.1.dist-info/METADATA
mvola_api_lib-1.4.1.dist-info/WHEEL
mvola_api_lib-1.4.1.dist-info/top_level.txt
mvola_api_lib-1.4.1.dist-info/RECORD
