Metadata-Version: 2.1
Name: mvola-api-lib
Version: 1.4.1
Summary: Une bibliothèque Python robuste pour l'intégration de l'API de paiement MVola
Home-page: https://github.com/Niainarisoa01/Mvola_API_Lib
Author: Niainarisoa
Author-email: Niainarisoa <niainarisoa.mail@gmail.com>
License: MIT
Project-URL: Homepage, https://github.com/Niainarisoa01/Mvola_API_Lib
Project-URL: Bug Tracker, https://github.com/Niainarisoa01/Mvola_API_Lib/issues
Project-URL: Documentation, https://niainarisoa01.github.io/Mvola_API_Lib
Project-URL: Changelog, https://github.com/Niainarisoa01/Mvola_API_Lib/blob/main/docs/changelog.md
Keywords: mvola,payment,api,madagascar,fintech,mobile money
Classifier: Development Status :: 4 - Beta
Classifier: Intended Audience :: Developers
Classifier: License :: OSI Approved :: MIT License
Classifier: Programming Language :: Python :: 3
Classifier: Programming Language :: Python :: 3.7
Classifier: Programming Language :: Python :: 3.8
Classifier: Programming Language :: Python :: 3.9
Classifier: Programming Language :: Python :: 3.10
Classifier: Programming Language :: Python :: 3.11
Classifier: Programming Language :: Python :: 3.12
Classifier: Programming Language :: Python :: 3.13
Classifier: Topic :: Software Development :: Libraries :: Python Modules
Classifier: Topic :: Office/Business :: Financial
Requires-Python: >=3.7
License-File: LICENSE
Requires-Dist: requests >=2.25.0
Requires-Dist: python-dotenv >=0.19.0
Provides-Extra: dev
Requires-Dist: pytest >=6.0 ; extra == 'dev'
Requires-Dist: pytest-cov >=2.12.0 ; extra == 'dev'
Requires-Dist: black >=21.5b2 ; extra == 'dev'
Requires-Dist: isort >=5.9.1 ; extra == 'dev'
Requires-Dist: flake8 >=3.9.2 ; extra == 'dev'
Provides-Extra: docs
Requires-Dist: mkdocs >=1.3.0 ; extra == 'docs'
Requires-Dist: mkdocs-material >=8.2.8 ; extra == 'docs'
Requires-Dist: mkdocstrings >=0.18.0 ; extra == 'docs'
Requires-Dist: mkdocstrings-python >=0.7.1 ; extra == 'docs'
Requires-Dist: mike >=1.1.2 ; extra == 'docs'
Provides-Extra: examples
Requires-Dist: flask >=2.0.0 ; extra == 'examples'
